AndroidTestingLibrary/Database.py
AndroidTestingLibrary/DatabaseElement.py
AndroidTestingLibrary/Device.py
AndroidTestingLibrary/DeviceConnector.py
AndroidTestingLibrary/Events.py
AndroidTestingLibrary/GeteventParser.py
AndroidTestingLibrary/GuiComponent.py
AndroidTestingLibrary/Helpers.py
AndroidTestingLibrary/MonkeyLabStrategy.py
AndroidTestingLibrary/RandomStrategy.py
AndroidTestingLibrary/TestingStrategy.py
AndroidTestingLibrary/__init__.py
AndroidTestingLibrary-1.1.1.dist-info/LICENSE.txt
AndroidTestingLibrary-1.1.1.dist-info/METADATA
AndroidTestingLibrary-1.1.1.dist-info/WHEEL
AndroidTestingLibrary-1.1.1.dist-info/top_level.txt
AndroidTestingLibrary-1.1.1.dist-info/RECORD
