Metadata-Version: 2.1
Name: AndroidTestingLibrary
Version: 1.1.1
Summary: Library for automated testing of Android applications
Home-page: https://gitlab.com/wm-csci435-f20/android-testing-library
Author: Carlos Bernal, Aidan Connor, Nathan Cooper, Miodrag Dronjak, Kaitlyn Huynh, Dominic Peterson, Denys Poshyvanyk, Evelyn Showalter, Daniel White
Author-email: ajconnor@email.wm.edu
License: UNKNOWN
Platform: UNKNOWN
Classifier: Programming Language :: Python :: 3
Classifier: License :: OSI Approved :: MIT License
Classifier: Operating System :: OS Independent
Requires-Python: >=3.7
Requires-Dist: pure-python-adb (>=0.3.0.dev0)
Requires-Dist: nltk (>=3.5)
